COPYING
MANIFEST.in
README.rst
bootstrap-buildout.py
buildout.cfg
requirements.txt
setup.py
version.txt
bob/__init__.py
bob.paper.biosig2016_replaymobile.egg-info/PKG-INFO
bob.paper.biosig2016_replaymobile.egg-info/SOURCES.txt
bob.paper.biosig2016_replaymobile.egg-info/dependency_links.txt
bob.paper.biosig2016_replaymobile.egg-info/entry_points.txt
bob.paper.biosig2016_replaymobile.egg-info/requires.txt
bob.paper.biosig2016_replaymobile.egg-info/top_level.txt
bob/paper/__init__.py
bob/paper/biosig2016_replaymobile/IQMFeatures.py
bob/paper/biosig2016_replaymobile/__init__.py
bob/paper/biosig2016_replaymobile/biosig2016.py
bob/paper/biosig2016_replaymobile/compute_iqm_features.py
bob/paper/biosig2016_replaymobile/evaluation.py
bob/paper/biosig2016_replaymobile/iqm_classifier.py
bob/paper/biosig2016_replaymobile/scoresReplayMobile.py
doc/conf.py
doc/index.rst
plots/Gabor_RBF_gamma000025_roc_curve.eps
plots/Gabor_RBF_gamma000025_roc_curve.pdf
plots/IQM_roc_curve.eps
plots/IQM_roc_curve.pdf
scores/gabor-svm-C_SVC-RBF-g0.00025.hdf5
scores/replaymobile_IqmScores_SVM.hdf5