Metadata-Version: 1.1
Name: bob.paper.biosig2016-replaymobile
Version: 1.0.4
Summary: Package for BioSIG-2016 paper on Replay-Mobile database.
Home-page: https://gitlab.idiap.ch/bob/bob.paper.biosig2016_replaymobile
Author: Sushil Bhattacharjee
Author-email: sushil.bhattacharjee@idiap.ch
License: GPLv3
Keywords: Bob package for BioSIG-2016 paper on ReplayMobile Face Presentation Attack Database
Platform: UNKNOWN
Classifier: Framework :: Bob
Classifier: Development Status :: 3 - Alpha
Classifier: Intended Audience :: Developers
Classifier: License :: OSI Approved :: GNU General Public License v3 (GPLv3)
Classifier: Natural Language :: English
Classifier: Programming Language :: Python
Classifier: Topic :: Scientific/Engineering :: Artificial Intelligence
